old_pdb/__init__.py
old_pdb/annotation.py
old_pdb/bookkeeping.py
old_pdb/coordinates.py
old_pdb/crystallography.py
old_pdb/general.py
old_pdb/heterogen.py
old_pdb/pdb_entry.py
old_pdb/primary.py
old_pdb/secondary.py
old_pdb-2.0.0.dist-info/LICENSE
old_pdb-2.0.0.dist-info/METADATA
old_pdb-2.0.0.dist-info/WHEEL
old_pdb-2.0.0.dist-info/top_level.txt
old_pdb-2.0.0.dist-info/RECORD
